nonelib.py
nonelib-0.0.1.dist-info/METADATA
nonelib-0.0.1.dist-info/WHEEL
nonelib-0.0.1.dist-info/top_level.txt
nonelib-0.0.1.dist-info/RECORD
