Metadata-Version: 2.1
Name: nonelib
Version: 0.0.1
Summary: f(x=None) ≡ f()
Home-page: https://github.com/marcgurevitx/nonelib
Author: Marc Gurevitx
Author-email: marcgurevitx@gmail.com
License: The Unlicense
Platform: UNKNOWN
